bmcsf
